{"status":"ok","data":{"13067":{"date":"2021-12-08","time":"09:45","days":2,"day1":{"tmin":null,"tmax":"4","type":"3","date":"2021-12-08"},"day2":{"tmin":"-1","tmax":"5","type":"8","date":"2021-12-09"}},"13168":{"date":"2021-12-08","time":"09:45","days":2,"day1":{"tmin":null,"tmax":"4","type":"3","date":"2021-12-08"},"day2":{"tmin":"-1","tmax":"6","type":"8","date":"2021-12-09"}},"13262":{"date":"2021-12-08","time":"09:45","days":2,"day1":{"tmin":null,"tmax":"7","type":"3","date":"2021-12-08"},"day2":{"tmin":"0","tmax":"8","type":"8","date":"2021-12-09"}},"13274":{"date":"2021-12-08","time":"09:45","days":2,"day1":{"tmin":null,"tmax":"6","type":"3","date":"2021-12-08"},"day2":{"tmin":"1","tmax":"7","type":"8","date":"2021-12-09"}},"13278":{"date":"2021-12-08","time":"09:45","days":2,"day1":{"tmin":null,"tmax":"6","type":"3","date":"2021-12-08"},"day2":{"tmin":"-1","tmax":"10","type":"8","date":"2021-12-09"}},"13295":{"date":"2021-12-08","time":"09:45","days":2,"day1":{"tmin":null,"tmax":"8","type":"3","date":"2021-12-08"},"day2":{"tmin":"-3","tmax":"4","type":"14","date":"2021-12-09"}},"13367":{"date":"2021-12-08","time":"09:45","days":2,"day1":{"tmin":null,"tmax":"3","type":"3","date":"2021-12-08"},"day2":{"tmin":"-2","tmax":"6","type":"14","date":"2021-12-09"}},"13376":{"date":"2021-12-08","time":"09:45","days":2,"day1":{"tmin":null,"tmax":"5","type":"3","date":"2021-12-08"},"day2":{"tmin":"-2","tmax":"8","type":"8","date":"2021-12-09"}},"13378":{"date":"2021-12-08","time":"09:45","days":2,"day1":{"tmin":null,"tmax":"4","type":"3","date":"2021-12-08"},"day2":{"tmin":"-2","tmax":"7","type":"8","date":"2021-12-09"}},"13388":{"date":"2021-12-08","time":"09:45","days":2,"day1":{"tmin":null,"tmax":"4","type":"10","date":"2021-12-08"},"day2":{"tmin":"-3","tmax":"9","type":"6","date":"2021-12-09"}}}}
